example_package_joerdis/__init__.py
example_package_joerdis/add.py
example_package_joerdis-0.0.1.dist-info/METADATA
example_package_joerdis-0.0.1.dist-info/WHEEL
example_package_joerdis-0.0.1.dist-info/top_level.txt
example_package_joerdis-0.0.1.dist-info/RECORD
